road_collisions_canada/__init__.py
road_collisions_canada/bin/__init__.py
road_collisions_canada/bin/load.py
road_collisions_canada/models/__init__.py
road_collisions_canada/models/collision.py
road_collisions_canada-0.0.2.dist-info/METADATA
road_collisions_canada-0.0.2.dist-info/WHEEL
road_collisions_canada-0.0.2.dist-info/entry_points.txt
road_collisions_canada-0.0.2.dist-info/top_level.txt
road_collisions_canada-0.0.2.dist-info/RECORD
